sthg_common_base/__init__.py
sthg_common_base/example/__init__.py
sthg_common_base/example/test_fastapi.py
sthg_common_base/example/test_service.py
sthg_common_base/example/test_utils.py
sthg_common_base/foundry_common/__init__.py
sthg_common_base/foundry_common/foundry_type.py
sthg_common_base/foundry_common/generator.py
sthg_common_base/response/__init__.py
sthg_common_base/response/exception.py
sthg_common_base/response/httpCodeEnum.py
sthg_common_base/response/json_serializer.py
sthg_common_base/response/response.py
sthg_common_base/test/api_test.py
sthg_common_base/test/test_http_code_enum.py
sthg_common_base/test/util.py
sthg_common_base/utils/__init__.py
sthg_common_base/utils/access_info.py
sthg_common_base/utils/code_utils.py
sthg_common_base/utils/constants.py
sthg_common_base/utils/log_util.py
sthg_common_base/utils/log_wrapper.py
sthg_common_base/utils/request_util.py
sthg_common_base/utils/sthg_common_constants.py
sthg_common_base/utils/utils.py
sthg_common_base/utils/vliad_common.py
sthg_common_base-0.4.8.7.dist-info/METADATA
sthg_common_base-0.4.8.7.dist-info/WHEEL
sthg_common_base-0.4.8.7.dist-info/top_level.txt
sthg_common_base-0.4.8.7.dist-info/RECORD
