Metadata-Version: 2.4
Name: sthg_common_base
Version: 0.4.8.7
Summary: Python FastApi logs
Home-page: https://github.com/yourusername/your_package_name
Author: DongQing
Author-email: DongQing <maoyouyu@163.com>
License: MIT
Project-URL: Homepage, https://github.com/yourusername/your_package_name
Classifier: Development Status :: 3 - Alpha
Classifier: Intended Audience :: Developers
Classifier: License :: OSI Approved :: MIT License
Classifier: Programming Language :: Python :: 3
Classifier: Programming Language :: Python :: 3.7
Classifier: Programming Language :: Python :: 3.8
Classifier: Programming Language :: Python :: 3.9
Classifier: Programming Language :: Python :: 3.10
Classifier: Programming Language :: Python :: 3.11
Classifier: Programming Language :: Python :: 3.12
Classifier: Programming Language :: Python :: 3.13
Requires-Python: >=3.7
Requires-Dist: fastapi>=0.68.0
Requires-Dist: uvicorn>=0.15.0
Requires-Dist: pydantic>=1.9.0
Requires-Dist: starlette>=0.19.1
Requires-Dist: sympy>=1.12
Requires-Dist: requests>=2.32.3
Dynamic: author
Dynamic: home-page
